pyaidoop_dl_models/__init__.py
pyaidoop_dl_models/mask_rcnn/__init__.py
pyaidoop_dl_models/mask_rcnn/config.py
pyaidoop_dl_models/mask_rcnn/inference.py
pyaidoop_dl_models/mask_rcnn/model.py
pyaidoop_dl_models/mask_rcnn/parallel_model.py
pyaidoop_dl_models/mask_rcnn/utils.py
pyaidoop_dl_models/mask_rcnn/visualize.py
pyaidoop_dl_models/yolo/__init__.py
pyaidoop_dl_models/yolo/backbone.py
pyaidoop_dl_models/yolo/common.py
pyaidoop_dl_models/yolo/config.py
pyaidoop_dl_models/yolo/dataset.py
pyaidoop_dl_models/yolo/inference.py
pyaidoop_dl_models/yolo/utils.py
pyaidoop_dl_models/yolo/yolov4.py
pyaidoop_dl_models-0.2.0.dist-info/LICENSE
pyaidoop_dl_models-0.2.0.dist-info/METADATA
pyaidoop_dl_models-0.2.0.dist-info/WHEEL
pyaidoop_dl_models-0.2.0.dist-info/top_level.txt
pyaidoop_dl_models-0.2.0.dist-info/RECORD
