Metadata-Version: 2.1
Name: pyaidoop-dl-models
Version: 0.2.0
Summary: AIdoop web-based platfrom library for robot application platform, AIdoop-R
Home-page: https://github.com/aidoop/pyaidoop-dl-models.git
Author: Jinwon Choi
Author-email: jinwon@ai-doop.com
License: MIT
Keywords: cooperative robot,web-based application,object detection,neural network,CNN,machine learning,computer vision
Platform: UNKNOWN
Classifier: Development Status :: 4 - Beta
Classifier: Intended Audience :: Developers
Classifier: License :: OSI Approved :: MIT License
Classifier: Natural Language :: English
Classifier: Operating System :: OS Independent
Classifier: Programming Language :: Python :: 3.6
Classifier: Programming Language :: Python :: 3.7
Classifier: Programming Language :: Python :: 3.8
Classifier: Topic :: Scientific/Engineering :: Artificial Intelligence
Classifier: Topic :: Scientific/Engineering :: Image Recognition
Classifier: Topic :: Software Development :: Libraries :: Python Modules
Requires-Dist: numpy
Requires-Dist: opencv-python
Requires-Dist: websocket-client
Requires-Dist: scipy (==1.4.1)
Requires-Dist: Pillow
Requires-Dist: cython
Requires-Dist: matplotlib
Requires-Dist: tensorflow (==2.5.0)
Requires-Dist: scikit-image (==0.16.2)
Requires-Dist: h5py
Requires-Dist: imgaug
Requires-Dist: IPython[all]
